swagger_codegen/__init__.py
swagger_codegen/api/__init__.py
swagger_codegen/api/adapter/__init__.py
swagger_codegen/api/adapter/aiohttp.py
swagger_codegen/api/adapter/base.py
swagger_codegen/api/adapter/httpx.py
swagger_codegen/api/adapter/params_converter.py
swagger_codegen/api/adapter/requests.py
swagger_codegen/api/base.py
swagger_codegen/api/client.py
swagger_codegen/api/configuration.py
swagger_codegen/api/exceptions.py
swagger_codegen/api/json.py
swagger_codegen/api/request.py
swagger_codegen/api/response.py
swagger_codegen/api/response_deserializer.py
swagger_codegen/api/types.py
swagger_codegen/cli/__init__.py
swagger_codegen/cli/config.py
swagger_codegen/cli/imports.py
swagger_codegen/cli/main.py
swagger_codegen/cli/setup_logging.py
swagger_codegen/cli/setup_renderer.py
swagger_codegen/parsing/__init__.py
swagger_codegen/parsing/data_type.py
swagger_codegen/parsing/data_type_parser.py
swagger_codegen/parsing/endpoint.py
swagger_codegen/parsing/endpoint_request.py
swagger_codegen/parsing/endpoint_response.py
swagger_codegen/parsing/loaders.py
swagger_codegen/parsing/parse.py
swagger_codegen/render/__init__.py
swagger_codegen/render/api.py
swagger_codegen/render/jinja_env.py
swagger_codegen/render/post_processors/__init__.py
swagger_codegen/render/post_processors/blackify.py
swagger_codegen/render/post_processors/post_processor.py
swagger_codegen/render/renderer.py
swagger_codegen/render/renderers/__init__.py
swagger_codegen/render/renderers/installable_package.py
swagger_codegen/render/renderers/package.py
swagger_codegen/render/templates.py
swagger_codegen/render/test_utils.py
swagger_codegen/render/utils.py
swagger_codegen/templates/package_renderer/api.jinja2
swagger_codegen/templates/package_renderer/client.jinja2
swagger_codegen/templates/package_renderer/dto.jinja2
swagger_codegen/templates/package_renderer/endpoint.jinja2
swagger_codegen/templates/package_renderer/endpoint_imports.jinja2
swagger_codegen/templates/package_renderer/manifest_in.jinja2
swagger_codegen-0.1.31.dist-info/entry_points.txt
swagger_codegen-0.1.31.dist-info/WHEEL
swagger_codegen-0.1.31.dist-info/METADATA
swagger_codegen-0.1.31.dist-info/RECORD
