Metadata-Version: 2.1
Name: swagger-codegen
Version: 0.1.31
Summary: Generate API clients by parsing Swagger definitions
Home-page: https://github.com/asyncee/swagger_codegen
License: MIT
Keywords: swagger-codegen,openapi,swagger,pydantic
Author: asyncee
Requires-Python: >=3.8,<4.0
Classifier: License :: OSI Approved :: MIT License
Classifier: Programming Language :: Python :: 3
Classifier: Programming Language :: Python :: 3.10
Classifier: Programming Language :: Python :: 3.8
Classifier: Programming Language :: Python :: 3.9
Provides-Extra: all
Provides-Extra: async
Provides-Extra: sync
Requires-Dist: aiohttp; extra == "async" or extra == "all"
Requires-Dist: boltons (>=20.2.1,<21.0.0)
Requires-Dist: click (>=7.1.1,<8.0.0)
Requires-Dist: httpx; extra == "async" or extra == "all"
Requires-Dist: inflection (>=0.5,<0.6)
Requires-Dist: jinja2 (>=2.11.1,<3.0.0)
Requires-Dist: multidict (>=5,<6)
Requires-Dist: pydantic (>=1.4,<2.0)
Requires-Dist: requests; extra == "sync" or extra == "all"
Requires-Dist: rich (>=9.6.1,<10.0.0)
Requires-Dist: schemathesis (==1.1.0)
Requires-Dist: toml (>=0.10.0,<0.11.0)
Requires-Dist: typer (>=0.3,<0.4)
Project-URL: Documentation, https://github.com/asyncee/swagger_codegen
Project-URL: Repository, https://github.com/asyncee/swagger_codegen
